parse_ecli/__init__.py
parse_ecli/decisions.json
parse_ecli/gerichte.json
parse_ecli/parse_ecli.py
parse_ecli/pattern.py
parse_ecli-0.9.5.dist-info/LICENSE.md
parse_ecli-0.9.5.dist-info/METADATA
parse_ecli-0.9.5.dist-info/WHEEL
parse_ecli-0.9.5.dist-info/entry_points.txt
parse_ecli-0.9.5.dist-info/top_level.txt
parse_ecli-0.9.5.dist-info/RECORD
