Metadata-Version: 2.1
Name: parse-ecli
Version: 0.9.5
Summary: Parse German ECLI
Home-page: http://github.com/kiersch/parse_ecli
Author: Philipp Kiersch
Author-email: philipp@kiersch.org
License: MIT
Platform: UNKNOWN
Classifier: Programming Language :: Python :: 3.8
Classifier: License :: OSI Approved :: MIT License
Classifier: Operating System :: OS Independent
Classifier: Intended Audience :: Legal Industry
Classifier: Topic :: Text Processing :: Filters
Classifier: Topic :: Text Processing :: Linguistic
Requires-Python: >=3.8
